pi_power_relay_moxad/__init__.py
pi_power_relay_moxad/functions.py
pi_power_relay_moxad/globals.py
pi_power_relay_moxad/pi_power_relay.py
pi_power_relay_moxad-2.0.2.dist-info/METADATA
pi_power_relay_moxad-2.0.2.dist-info/WHEEL
pi_power_relay_moxad-2.0.2.dist-info/entry_points.txt
pi_power_relay_moxad-2.0.2.dist-info/licenses/LICENSE.txt
pi_power_relay_moxad-2.0.2.dist-info/RECORD
