Metadata-Version: 2.1
Name: pi_power_relay_moxad
Version: 2.0.2
Summary: power cycle device from a Raspberry Pi when network connectivity lost
Project-URL: Homepage, https://github.com/rjwhite/pi-power-relay
Author-email: RJ White <rj.white@moxad.com>
License-File: LICENSE.txt
Classifier: Intended Audience :: End Users/Desktop
Classifier: License :: OSI Approved :: MIT License
Classifier: Natural Language :: English
Classifier: Operating System :: POSIX :: Linux
Classifier: Programming Language :: Python
Classifier: Programming Language :: Python :: 2
Classifier: Programming Language :: Python :: 3
Requires-Dist: rpi-gpio
